<?xml version="1.0" encoding="UTF-8"?>
<!DOCTYPE mapper PUBLIC "-//mybatis.org//DTD Mapper 3.0//EN" "http://mybatis.org/dtd/mybatis-3-mapper.dtd">
<mapper namespace="com.talkweb.ei.outmanager.dao.VOutUserdutyMapper">
  <resultMap id="BaseResultMap" type="com.talkweb.ei.outmanager.model.VOutUserduty">
    <!--
      WARNING - @mbg.generated
      This element is automatically generated by MyBatis Generator, do not modify.
      This element was generated on Fri Jun 30 16:57:05 CST 2017.
    -->
    
    <result column="ID" jdbcType="VARCHAR" property="id" />
    <result column="USERID" jdbcType="VARCHAR" property="userid" />
    <result column="NAME" jdbcType="VARCHAR" property="name" />
    <result column="UNIT" jdbcType="VARCHAR" property="unit" />
    <result column="DUTYID" jdbcType="VARCHAR" property="dutyid" />
    <result column="DUTY" jdbcType="VARCHAR" property="duty" />
    <result column="REMARK" jdbcType="VARCHAR" property="remark" />
    <result column="UNITID" jdbcType="VARCHAR" property="unitid" />
    <result column="SELFORG" jdbcType="VARCHAR" property="selforg" />
    <result column="SUBORG" jdbcType="VARCHAR" property="suborg" />
  </resultMap>
  <sql id="Example_Where_Clause">
    <!--
      WARNING - @mbg.generated
      This element is automatically generated by MyBatis Generator, do not modify.
      This element was generated on Fri Jun 30 16:57:05 CST 2017.
    -->
    <where>
      <foreach collection="oredCriteria" item="criteria" separator="or">
        <if test="criteria.valid">
          <trim prefix="(" prefixOverrides="and" suffix=")">
            <foreach collection="criteria.criteria" item="criterion">
              <choose>
                <when test="criterion.noValue">
                  and ${criterion.condition}
                </when>
                <when test="criterion.singleValue">
                  and ${criterion.condition} #{criterion.value}
                </when>
                <when test="criterion.betweenValue">
                  and ${criterion.condition} #{criterion.value} and #{criterion.secondValue}
                </when>
                <when test="criterion.listValue">
                  and ${criterion.condition}
                  <foreach close=")" collection="criterion.value" item="listItem" open="(" separator=",">
                    #{listItem}
                  </foreach>
                </when>
              </choose>
            </foreach>
          </trim>
        </if>
      </foreach>
    </where>
  </sql>
  <sql id="Update_By_Example_Where_Clause">
    <!--
      WARNING - @mbg.generated
      This element is automatically generated by MyBatis Generator, do not modify.
      This element was generated on Fri Jun 30 16:57:05 CST 2017.
    -->
    <where>
      <foreach collection="example.oredCriteria" item="criteria" separator="or">
        <if test="criteria.valid">
          <trim prefix="(" prefixOverrides="and" suffix=")">
            <foreach collection="criteria.criteria" item="criterion">
              <choose>
                <when test="criterion.noValue">
                  and ${criterion.condition}
                </when>
                <when test="criterion.singleValue">
                  and ${criterion.condition} #{criterion.value}
                </when>
                <when test="criterion.betweenValue">
                  and ${criterion.condition} #{criterion.value} and #{criterion.secondValue}
                </when>
                <when test="criterion.listValue">
                  and ${criterion.condition}
                  <foreach close=")" collection="criterion.value" item="listItem" open="(" separator=",">
                    #{listItem}
                  </foreach>
                </when>
              </choose>
            </foreach>
          </trim>
        </if>
      </foreach>
    </where>
  </sql>
  <sql id="Base_Column_List">
    <!--
      WARNING - @mbg.generated
      This element is automatically generated by MyBatis Generator, do not modify.
      This element was generated on Fri Jun 30 16:57:05 CST 2017.
    -->
   ID, USERID, NAME, UNIT, DUTYID, DUTY, REMARK, UNITID, SELFORG, SUBORG
  </sql>
  <select id="selectByExample" parameterType="com.talkweb.ei.outmanager.model.VOutUserdutyExample" resultMap="BaseResultMap">
    <!--
      WARNING - @mbg.generated
      This element is automatically generated by MyBatis Generator, do not modify.
      This element was generated on Fri Jun 30 16:57:05 CST 2017.
    -->
    select
    <if test="distinct">
      distinct
    </if>
    <include refid="Base_Column_List" />
    from v_out_userduty
    <if test="_parameter != null">
      <include refid="Example_Where_Clause" />
    </if>
    <if test="orderByClause != null">
      order by ${orderByClause}
    </if>
  </select>
  <delete id="deleteByExample" parameterType="com.talkweb.ei.outmanager.model.VOutUserdutyExample">
    <!--
      WARNING - @mbg.generated
      This element is automatically generated by MyBatis Generator, do not modify.
      This element was generated on Fri Jun 30 16:57:05 CST 2017.
    -->
    delete from v_out_userduty
    <if test="_parameter != null">
      <include refid="Example_Where_Clause" />
    </if>
  </delete>
  <insert id="insert" parameterType="com.talkweb.ei.outmanager.model.VOutUserduty">
    <!--
      WARNING - @mbg.generated
      This element is automatically generated by MyBatis Generator, do not modify.
      This element was generated on Fri Jun 30 16:57:05 CST 2017.
    -->
    insert into v_out_userduty (USERID, NAME, UNIT, 
      DUTYID, DUTY, REMARK, 
      UNITID, SELFORG, SUBORG
      )
    values (#{userid,jdbcType=VARCHAR}, #{name,jdbcType=VARCHAR}, #{unit,jdbcType=VARCHAR}, 
      #{dutyid,jdbcType=VARCHAR}, #{duty,jdbcType=VARCHAR}, #{remark,jdbcType=VARCHAR}, 
      #{unitid,jdbcType=VARCHAR}, #{selforg,jdbcType=VARCHAR}, #{suborg,jdbcType=VARCHAR}
      )
  </insert>
  <insert id="insertSelective" parameterType="com.talkweb.ei.outmanager.model.VOutUserduty">
    <!--
      WARNING - @mbg.generated
      This element is automatically generated by MyBatis Generator, do not modify.
      This element was generated on Fri Jun 30 16:57:05 CST 2017.
    -->
    insert into v_out_userduty
    <trim prefix="(" suffix=")" suffixOverrides=",">
      <if test="userid != null">
        USERID,
      </if>
      <if test="name != null">
        NAME,
      </if>
      <if test="unit != null">
        UNIT,
      </if>
      <if test="dutyid != null">
        DUTYID,
      </if>
      <if test="duty != null">
        DUTY,
      </if>
      <if test="remark != null">
        REMARK,
      </if>
      <if test="unitid != null">
        UNITID,
      </if>
      <if test="selforg != null">
        SELFORG,
      </if>
      <if test="suborg != null">
        SUBORG,
      </if>
    </trim>
    <trim prefix="values (" suffix=")" suffixOverrides=",">
      <if test="userid != null">
        #{userid,jdbcType=VARCHAR},
      </if>
      <if test="name != null">
        #{name,jdbcType=VARCHAR},
      </if>
      <if test="unit != null">
        #{unit,jdbcType=VARCHAR},
      </if>
      <if test="dutyid != null">
        #{dutyid,jdbcType=VARCHAR},
      </if>
      <if test="duty != null">
        #{duty,jdbcType=VARCHAR},
      </if>
      <if test="remark != null">
        #{remark,jdbcType=VARCHAR},
      </if>
      <if test="unitid != null">
        #{unitid,jdbcType=VARCHAR},
      </if>
      <if test="selforg != null">
        #{selforg,jdbcType=VARCHAR},
      </if>
      <if test="suborg != null">
        #{suborg,jdbcType=VARCHAR},
      </if>
    </trim>
  </insert>
  <select id="countByExample" parameterType="com.talkweb.ei.outmanager.model.VOutUserdutyExample" resultType="java.lang.Long">
    <!--
      WARNING - @mbg.generated
      This element is automatically generated by MyBatis Generator, do not modify.
      This element was generated on Fri Jun 30 16:57:05 CST 2017.
    -->
    select count(*) from v_out_userduty
    <if test="_parameter != null">
      <include refid="Example_Where_Clause" />
    </if>
  </select>
  <update id="updateByExampleSelective" parameterType="map">
    <!--
      WARNING - @mbg.generated
      This element is automatically generated by MyBatis Generator, do not modify.
      This element was generated on Fri Jun 30 16:57:05 CST 2017.
    -->
    update v_out_userduty
    <set>
      <if test="record.userid != null">
        USERID = #{record.userid,jdbcType=VARCHAR},
      </if>
      <if test="record.name != null">
        NAME = #{record.name,jdbcType=VARCHAR},
      </if>
      <if test="record.unit != null">
        UNIT = #{record.unit,jdbcType=VARCHAR},
      </if>
      <if test="record.dutyid != null">
        DUTYID = #{record.dutyid,jdbcType=VARCHAR},
      </if>
      <if test="record.duty != null">
        DUTY = #{record.duty,jdbcType=VARCHAR},
      </if>
      <if test="record.remark != null">
        REMARK = #{record.remark,jdbcType=VARCHAR},
      </if>
      <if test="record.unitid != null">
        UNITID = #{record.unitid,jdbcType=VARCHAR},
      </if>
      <if test="record.selforg != null">
        SELFORG = #{record.selforg,jdbcType=VARCHAR},
      </if>
      <if test="record.suborg != null">
        SUBORG = #{record.suborg,jdbcType=VARCHAR},
      </if>
    </set>
    <if test="_parameter != null">
      <include refid="Update_By_Example_Where_Clause" />
    </if>
  </update>
  <update id="updateByExample" parameterType="map">
    <!--
      WARNING - @mbg.generated
      This element is automatically generated by MyBatis Generator, do not modify.
      This element was generated on Fri Jun 30 16:57:05 CST 2017.
    -->
    update v_out_userduty
    set USERID = #{record.userid,jdbcType=VARCHAR},
      NAME = #{record.name,jdbcType=VARCHAR},
      UNIT = #{record.unit,jdbcType=VARCHAR},
      DUTYID = #{record.dutyid,jdbcType=VARCHAR},
      DUTY = #{record.duty,jdbcType=VARCHAR},
      REMARK = #{record.remark,jdbcType=VARCHAR},
      UNITID = #{record.unitid,jdbcType=VARCHAR},
      SELFORG = #{record.selforg,jdbcType=VARCHAR},
      SUBORG = #{record.suborg,jdbcType=VARCHAR}
    <if test="_parameter != null">
      <include refid="Update_By_Example_Where_Clause" />
    </if>
  </update>
  
  
  
 <!-- 分页查询 -->
    <select id="selectPageByExample" parameterType="com.talkweb.ei.outmanager.model.VOutUserdutyExample" resultMap="BaseResultMap">
    <!--
      WARNING - @mbg.generated
      This element is automatically generated by MyBatis Generator, do not modify.
      This element was generated on Tue May 02 13:19:15 CST 2017.
    -->
    
    
    <!-- 分页 -->
     SELECT * FROM   
	(  
		SELECT DATA.*, ROWNUM RN   
		FROM (
     <!-- 分页 -->
    
    select
    <if test="distinct">
      distinct
    </if>
    <include refid="Base_Column_List" />
    from v_out_userduty
    <if test="_parameter != null">
      <include refid="Example_Where_Clause" />
    </if>
    <if test="orderByClause != null">
      order by ${orderByClause}
    </if>
    
    
    <!-- 分页 -->
    ) DATA   
	)  
	

    WHERE RN BETWEEN ${offset} AND ${limit} 
    <!-- 分页 -->
    
  </select> 
  
  
  
  
  
  
</mapper>